my_library_mk_005/__init__.py
my_library_mk_005/input.py
my_library_mk_005/my_module.py
my_library_mk_005/cpp/my_code.cpp
my_library_mk_005-0.1.dist-info/METADATA
my_library_mk_005-0.1.dist-info/WHEEL
my_library_mk_005-0.1.dist-info/top_level.txt
my_library_mk_005-0.1.dist-info/RECORD
