Metadata-Version: 2.1
Name: my_library_mk_005
Version: 0.1
Summary: A Python library
Author: Mushaim Khan
Author-email: mushaimk01@gmail.com
